safely/__init__.py
safely/api.py
safely/core.py
safely/py.typed
safely-0.2.1.dist-info/LICENSE
safely-0.2.1.dist-info/WHEEL
safely-0.2.1.dist-info/METADATA
safely-0.2.1.dist-info/RECORD
